{
  "005930": {
    "price": 188200,
    "chg": 0,
    "basePrice": 188200,
    "high": "189700",
    "low": "181000",
    "open": "186100",
    "vol": "0",
    "dataSource": "live",
    "updatedAt": "2026-03-06T13:08:57"
  },
  "000660": {
    "price": 924000,
    "chg": 0,
    "basePrice": 924000,
    "high": "938000",
    "low": "885000",
    "open": "912000",
    "vol": "0",
    "dataSource": "live",
    "updatedAt": "2026-03-06T13:08:58"
  },
  "035420": {
    "price": 222500,
    "chg": 0,
    "basePrice": 222500,
    "high": "225500",
    "low": "216000",
    "open": "216000",
    "vol": "0",
    "dataSource": "live",
    "updatedAt": "2026-03-06T13:08:59"
  },
  "005380": {
    "price": 553000,
    "chg": 0,
    "basePrice": 553000,
    "high": "564000",
    "low": "530000",
    "open": "532000",
    "vol": "0",
    "dataSource": "live",
    "updatedAt": "2026-03-06T13:09:00"
  },
  "068270": {
    "price": 212500,
    "chg": 0,
    "basePrice": 212500,
    "high": "216500",
    "low": "206500",
    "open": "214500",
    "vol": "0",
    "dataSource": "live",
    "updatedAt": "2026-03-06T13:09:01"
  },
  "051910": {
    "price": 326500,
    "chg": 0,
    "basePrice": 326500,
    "high": "328000",
    "low": "307500",
    "open": "317500",
    "vol": "0",
    "dataSource": "live",
    "updatedAt": "2026-03-06T13:09:02"
  },
  "006400": {
    "price": 410500,
    "chg": 0,
    "basePrice": 410500,
    "high": "411500",
    "low": "385500",
    "open": "388500",
    "vol": "0",
    "dataSource": "live",
    "updatedAt": "2026-03-06T13:09:03"
  },
  "105560": {
    "price": 147400,
    "chg": 0,
    "basePrice": 147400,
    "high": "150300",
    "low": "143200",
    "open": "144500",
    "vol": "0",
    "dataSource": "live",
    "updatedAt": "2026-03-06T13:09:04"
  },
  "034020": {
    "price": 98000,
    "chg": 0,
    "basePrice": 98000,
    "high": "98200",
    "low": "88600",
    "open": "88600",
    "vol": "0",
    "dataSource": "live",
    "updatedAt": "2026-03-06T13:09:05"
  },
  "000270": {
    "price": 167000,
    "chg": 0,
    "basePrice": 167000,
    "high": "169600",
    "low": "161000",
    "open": "161100",
    "vol": "0",
    "dataSource": "live",
    "updatedAt": "2026-03-06T13:09:05"
  },
  "035720": {
    "price": 53600,
    "chg": 0,
    "basePrice": 53600,
    "high": "54400",
    "low": "50500",
    "open": "50500",
    "vol": "0",
    "dataSource": "live",
    "updatedAt": "2026-03-06T13:09:06"
  },
  "207940": {
    "price": 1644000,
    "chg": 0,
    "basePrice": 1644000,
    "high": "1668000",
    "low": "1599000",
    "open": "1614000",
    "vol": "0",
    "dataSource": "live",
    "updatedAt": "2026-03-06T13:09:07"
  },
  "329180": {
    "price": 554000,
    "chg": 0,
    "basePrice": 554000,
    "high": "564000",
    "low": "536000",
    "open": "538000",
    "vol": "0",
    "dataSource": "live",
    "updatedAt": "2026-03-06T13:09:08"
  },
  "012450": {
    "price": 1481000,
    "chg": 0,
    "basePrice": 1481000,
    "high": "1540000",
    "low": "1368000",
    "open": "1414000",
    "vol": "0",
    "dataSource": "live",
    "updatedAt": "2026-03-06T13:09:09"
  },
  "247540": {
    "price": 202500,
    "chg": 0,
    "basePrice": 202500,
    "high": "205500",
    "low": "191300",
    "open": "194600",
    "vol": "0",
    "dataSource": "live",
    "updatedAt": "2026-03-06T13:09:10"
  },
  "042700": {
    "price": 333500,
    "chg": 0,
    "basePrice": 333500,
    "high": "334000",
    "low": "305000",
    "open": "326000",
    "vol": "0",
    "dataSource": "live",
    "updatedAt": "2026-03-06T13:09:11"
  }
}