[
  {
    "code": "005930",
    "name": "삼성전자",
    "sector": "반도체",
    "price": 190000,
    "chg": 9.51,
    "open": 193000,
    "high": 194800,
    "low": 187700,
    "vol": 25474586,
    "prev": 173500,
    "source": "yahoo",
    "updatedAt": "2026-03-11T22:15:48.791534+09:00"
  },
  {
    "code": "000660",
    "name": "SK하이닉스",
    "sector": "반도체",
    "price": 955000,
    "chg": 14.23,
    "open": 954000,
    "high": 985000,
    "low": 941000,
    "vol": 4149341,
    "prev": 836000,
    "source": "yahoo",
    "updatedAt": "2026-03-11T22:15:48.791534+09:00"
  },
  {
    "code": "035420",
    "name": "NAVER",
    "sector": "IT",
    "price": 222000,
    "chg": 1.6,
    "open": 227000,
    "high": 230000,
    "low": 221000,
    "vol": 757145,
    "prev": 218500,
    "source": "yahoo",
    "updatedAt": "2026-03-11T22:15:48.791534+09:00"
  },
  {
    "code": "035720",
    "name": "카카오",
    "sector": "IT",
    "price": 50900,
    "chg": 0.99,
    "open": 52500,
    "high": 53200,
    "low": 50600,
    "vol": 1975641,
    "prev": 50400,
    "source": "yahoo",
    "updatedAt": "2026-03-11T22:15:48.791534+09:00"
  },
  {
    "code": "051910",
    "name": "LG화학",
    "sector": "화학",
    "price": 315500,
    "chg": 5.17,
    "open": 321500,
    "high": 329500,
    "low": 312000,
    "vol": 217879,
    "prev": 300000,
    "source": "yahoo",
    "updatedAt": "2026-03-11T22:15:48.791534+09:00"
  },
  {
    "code": "006400",
    "name": "삼성SDI",
    "sector": "2차전지",
    "price": 400000,
    "chg": 2.83,
    "open": 413500,
    "high": 419000,
    "low": 394500,
    "vol": 545880,
    "prev": 389000,
    "source": "yahoo",
    "updatedAt": "2026-03-11T22:15:48.791534+09:00"
  },
  {
    "code": "207940",
    "name": "삼성바이오로직스",
    "sector": "바이오",
    "price": 1657000,
    "chg": 4.94,
    "open": 1630000,
    "high": 1693000,
    "low": 1626000,
    "vol": 48088,
    "prev": 1579000,
    "source": "yahoo",
    "updatedAt": "2026-03-11T22:15:48.791534+09:00"
  },
  {
    "code": "068270",
    "name": "셀트리온",
    "sector": "바이오",
    "price": 209000,
    "chg": 2.45,
    "open": 209500,
    "high": 214000,
    "low": 207000,
    "vol": 430951,
    "prev": 204000,
    "source": "yahoo",
    "updatedAt": "2026-03-11T22:15:48.791534+09:00"
  },
  {
    "code": "005380",
    "name": "현대차",
    "sector": "자동차",
    "price": 530000,
    "chg": 4.54,
    "open": 550000,
    "high": 561000,
    "low": 523000,
    "vol": 1450037,
    "prev": 507000,
    "source": "yahoo",
    "updatedAt": "2026-03-11T22:15:48.791534+09:00"
  },
  {
    "code": "000270",
    "name": "기아",
    "sector": "자동차",
    "price": 162000,
    "chg": 5.61,
    "open": 169000,
    "high": 170400,
    "low": 160500,
    "vol": 1247072,
    "prev": 153400,
    "source": "yahoo",
    "updatedAt": "2026-03-11T22:15:48.791534+09:00"
  },
  {
    "code": "003550",
    "name": "LG",
    "sector": "지주",
    "price": 93300,
    "chg": 4.48,
    "open": 95400,
    "high": 96500,
    "low": 92500,
    "vol": 425611,
    "prev": 89300,
    "source": "yahoo",
    "updatedAt": "2026-03-11T22:15:48.791534+09:00"
  },
  {
    "code": "055550",
    "name": "신한지주",
    "sector": "금융",
    "price": 91100,
    "chg": 2.94,
    "open": 90900,
    "high": 94200,
    "low": 90300,
    "vol": 2055895,
    "prev": 88500,
    "source": "yahoo",
    "updatedAt": "2026-03-11T22:15:48.791534+09:00"
  },
  {
    "code": "105560",
    "name": "KB금융",
    "sector": "금융",
    "price": 151300,
    "chg": 6.1,
    "open": 154100,
    "high": 157700,
    "low": 149900,
    "vol": 1451829,
    "prev": 142600,
    "source": "yahoo",
    "updatedAt": "2026-03-11T22:15:48.791534+09:00"
  },
  {
    "code": "012330",
    "name": "현대모비스",
    "sector": "자동차",
    "price": 423000,
    "chg": 3.42,
    "open": 443000,
    "high": 447000,
    "low": 419500,
    "vol": 336863,
    "prev": 409000,
    "source": "yahoo",
    "updatedAt": "2026-03-11T22:15:48.791534+09:00"
  },
  {
    "code": "028260",
    "name": "삼성물산",
    "sector": "지주",
    "price": 283500,
    "chg": 4.81,
    "open": 282000,
    "high": 295500,
    "low": 278000,
    "vol": 427416,
    "prev": 270500,
    "source": "yahoo",
    "updatedAt": "2026-03-11T22:15:48.791534+09:00"
  },
  {
    "code": "066570",
    "name": "LG전자",
    "sector": "전자",
    "price": 117900,
    "chg": 3.97,
    "open": 118600,
    "high": 122500,
    "low": 116500,
    "vol": 1047058,
    "prev": 113400,
    "source": "yahoo",
    "updatedAt": "2026-03-11T22:15:48.791534+09:00"
  },
  {
    "code": "096770",
    "name": "SK이노베이션",
    "sector": "에너지",
    "price": 119500,
    "chg": 1.1,
    "open": 120200,
    "high": 126400,
    "low": 119000,
    "vol": 832752,
    "prev": 118200,
    "source": "yahoo",
    "updatedAt": "2026-03-11T22:15:48.791534+09:00"
  },
  {
    "code": "034730",
    "name": "SK",
    "sector": "지주",
    "price": 359500,
    "chg": 9.27,
    "open": 401500,
    "high": 402500,
    "low": 351000,
    "vol": 1048503,
    "prev": 329000,
    "source": "yahoo",
    "updatedAt": "2026-03-11T22:15:48.791534+09:00"
  },
  {
    "code": "017670",
    "name": "SK텔레콤",
    "sector": "통신",
    "price": 77900,
    "chg": 2.77,
    "open": 78200,
    "high": 79900,
    "low": 77300,
    "vol": 1133458,
    "prev": 75800,
    "source": "yahoo",
    "updatedAt": "2026-03-11T22:15:48.791534+09:00"
  },
  {
    "code": "030200",
    "name": "KT",
    "sector": "통신",
    "price": 59900,
    "chg": 0.67,
    "open": 61100,
    "high": 61500,
    "low": 59700,
    "vol": 361354,
    "prev": 59500,
    "source": "yahoo",
    "updatedAt": "2026-03-11T22:15:48.791534+09:00"
  }
]